LICENSE
MANIFEST.in
NOTICE
README.md
pyproject.toml
setup.cfg
setup.py
src/ros_cdk_brainindustrial/__init__.py
src/ros_cdk_brainindustrial/py.typed
src/ros_cdk_brainindustrial.egg-info/PKG-INFO
src/ros_cdk_brainindustrial.egg-info/SOURCES.txt
src/ros_cdk_brainindustrial.egg-info/dependency_links.txt
src/ros_cdk_brainindustrial.egg-info/requires.txt
src/ros_cdk_brainindustrial.egg-info/top_level.txt
src/ros_cdk_brainindustrial/_jsii/__init__.py
src/ros_cdk_brainindustrial/_jsii/ros-cdk-brainindustrial@1.0.24.jsii.tgz